aws_cdk_config/__init__.py
aws_cdk_config/config.py
aws_cdk_config/exceptions.py
aws_cdk_config/input.py
aws_cdk_config-0.1.2.dist-info/LICENSE
aws_cdk_config-0.1.2.dist-info/METADATA
aws_cdk_config-0.1.2.dist-info/WHEEL
aws_cdk_config-0.1.2.dist-info/RECORD
