Metadata-Version: 2.1
Name: aws-cdk-config
Version: 0.1.2
Summary: Provides typed and validated inputs for Cdk projects
Author: Mathew Moon
Author-email: me@mathewmoon.net
Requires-Python: >=3.11,<4.0
Classifier: Programming Language :: Python :: 3
Classifier: Programming Language :: Python :: 3.11
Classifier: Programming Language :: Python :: 3.12
Requires-Dist: pyyaml (>=6.0.1,<7.0.0)
Requires-Dist: typeguard (>=2.13.3,<3.0.0)
